tbwk/Measurement.py
tbwk/Properties.py
tbwk/RawOpener.py
tbwk/Worksheet.py
tbwk/__init__.py
tbwk_opener-0.1.1.dist-info/LICENSE
tbwk_opener-0.1.1.dist-info/METADATA
tbwk_opener-0.1.1.dist-info/WHEEL
tbwk_opener-0.1.1.dist-info/top_level.txt
tbwk_opener-0.1.1.dist-info/RECORD
