Metadata-Version: 2.1
Name: tbwk-opener
Version: 0.1.1
Summary: An tool to open tbwk files generated by NanoDrop 2000
Home-page: https://github.com/Gillingham-Lab/tbwk-opener
Author: Basilius Sauter
Author-email: basilius.sauter@gmail.com
Classifier: Programming Language :: Python :: 3
Classifier: License :: OSI Approved :: MIT License
Classifier: Operating System :: OS Independent
Classifier: Intended Audience :: Science/Research
Classifier: Topic :: Scientific/Engineering :: Chemistry
Classifier: Topic :: Scientific/Engineering :: Bio-Informatics
Classifier: Topic :: Software Development :: Libraries :: Python Modules
Classifier: Topic :: Utilities
Requires-Python: >=3.6
License-File: LICENSE
Requires-Dist: numpy
Requires-Dist: scipy
Requires-Dist: defusedxml
